{
  "info": {
    "name": "BhutanMart API",
    "description": "Complete API collection for BhutanMart E-commerce Platform",
    "version": "1.0.0"
  },
  "item": [
    {
      "name": "Health Check",
      "request": {
        "method": "GET",
        "url": "http://localhost:5000/health",
        "header": []
      }
    },
    {
      "name": "Authentication",
      "item": [
        {
          "name": "Register User",
          "request": {
            "method": "POST",
            "url": "http://localhost:5000/api/auth/register",
            "header": [
              {
                "key": "Content-Type",
                "value": "application/json"
              }
            ],
            "body": {
              "mode": "raw",
              "raw": "{\n  \"name\": \"John Doe\",\n  \"email\": \"john@example.com\",\n  \"password\": \"password123\",\n  \"role\": \"customer\"\n}"
            }
          }
        },
        {
          "name": "Login User",
          "request": {
            "method": "POST",
            "url": "http://localhost:5000/api/auth/login",
            "header": [
              {
                "key": "Content-Type",
                "value": "application/json"
              }
            ],
            "body": {
              "mode": "raw",
              "raw": "{\n  \"email\": \"john@example.com\",\n  \"password\": \"password123\"\n}"
            }
          }
        },
        {
          "name": "Get Current User",
          "request": {
            "method": "GET",
            "url": "http://localhost:5000/api/auth/me",
            "header": [
              {
                "key": "Authorization",
                "value": "Bearer YOUR_TOKEN_HERE"
              }
            ]
          }
        },
        {
          "name": "Logout User",
          "request": {
            "method": "POST",
            "url": "http://localhost:5000/api/auth/logout",
            "header": [
              {
                "key": "Authorization",
                "value": "Bearer YOUR_TOKEN_HERE"
              }
            ]
          }
        }
      ]
    },
    {
      "name": "Categories",
      "item": [
        {
          "name": "Get All Categories",
          "request": {
            "method": "GET",
            "url": "http://localhost:5000/api/categories?page=1&limit=10",
            "header": []
          }
        },
        {
          "name": "Get Category by ID",
          "request": {
            "method": "GET",
            "url": "http://localhost:5000/api/categories/CATEGORY_ID",
            "header": []
          }
        },
        {
          "name": "Create Category",
          "request": {
            "method": "POST",
            "url": "http://localhost:5000/api/categories",
            "header": [
              {
                "key": "Authorization",
                "value": "Bearer YOUR_ADMIN_TOKEN"
              },
              {
                "key": "Content-Type",
                "value": "application/json"
              }
            ],
            "body": {
              "mode": "raw",
              "raw": "{\n  \"name\": \"Electronics\",\n  \"description\": \"Electronic devices and gadgets\"\n}"
            }
          }
        }
      ]
    },
    {
      "name": "Products",
      "item": [
        {
          "name": "Get All Products",
          "request": {
            "method": "GET",
            "url": "http://localhost:5000/api/products?page=1&limit=10&sortBy=price_asc",
            "header": []
          }
        },
        {
          "name": "Get Product by ID",
          "request": {
            "method": "GET",
            "url": "http://localhost:5000/api/products/PRODUCT_ID",
            "header": []
          }
        },
        {
          "name": "Create Product",
          "request": {
            "method": "POST",
            "url": "http://localhost:5000/api/products",
            "header": [
              {
                "key": "Authorization",
                "value": "Bearer YOUR_SELLER_TOKEN"
              },
              {
                "key": "Content-Type",
                "value": "application/json"
              }
            ],
            "body": {
              "mode": "raw",
              "raw": "{\n  \"name\": \"Wireless Headphones\",\n  \"description\": \"Premium wireless headphones\",\n  \"categoryId\": \"CATEGORY_ID\",\n  \"price\": 99.99,\n  \"stock\": 50,\n  \"tags\": [\"electronics\", \"audio\"],\n  \"variants\": [\n    {\"color\": \"Black\", \"sku\": \"WH-001-BLK\"},\n    {\"color\": \"White\", \"sku\": \"WH-001-WHT\"}\n  ]\n}"
            }
          }
        },
        {
          "name": "Update Product",
          "request": {
            "method": "PUT",
            "url": "http://localhost:5000/api/products/PRODUCT_ID",
            "header": [
              {
                "key": "Authorization",
                "value": "Bearer YOUR_SELLER_TOKEN"
              },
              {
                "key": "Content-Type",
                "value": "application/json"
              }
            ],
            "body": {
              "mode": "raw",
              "raw": "{\n  \"price\": 89.99,\n  \"stock\": 40\n}"
            }
          }
        },
        {
          "name": "Delete Product",
          "request": {
            "method": "DELETE",
            "url": "http://localhost:5000/api/products/PRODUCT_ID",
            "header": [
              {
                "key": "Authorization",
                "value": "Bearer YOUR_SELLER_TOKEN"
              }
            ]
          }
        }
      ]
    },
    {
      "name": "Cart",
      "item": [
        {
          "name": "Get Cart",
          "request": {
            "method": "GET",
            "url": "http://localhost:5000/api/cart",
            "header": [
              {
                "key": "Authorization",
                "value": "Bearer YOUR_TOKEN_HERE"
              }
            ]
          }
        },
        {
          "name": "Add to Cart",
          "request": {
            "method": "POST",
            "url": "http://localhost:5000/api/cart/add",
            "header": [
              {
                "key": "Authorization",
                "value": "Bearer YOUR_TOKEN_HERE"
              },
              {
                "key": "Content-Type",
                "value": "application/json"
              }
            ],
            "body": {
              "mode": "raw",
              "raw": "{\n  \"productId\": \"PRODUCT_ID\",\n  \"quantity\": 2\n}"
            }
          }
        },
        {
          "name": "Update Cart Item",
          "request": {
            "method": "PUT",
            "url": "http://localhost:5000/api/cart/update",
            "header": [
              {
                "key": "Authorization",
                "value": "Bearer YOUR_TOKEN_HERE"
              },
              {
                "key": "Content-Type",
                "value": "application/json"
              }
            ],
            "body": {
              "mode": "raw",
              "raw": "{\n  \"productId\": \"PRODUCT_ID\",\n  \"quantity\": 5\n}"
            }
          }
        },
        {
          "name": "Remove from Cart",
          "request": {
            "method": "DELETE",
            "url": "http://localhost:5000/api/cart/remove/PRODUCT_ID",
            "header": [
              {
                "key": "Authorization",
                "value": "Bearer YOUR_TOKEN_HERE"
              }
            ]
          }
        },
        {
          "name": "Clear Cart",
          "request": {
            "method": "DELETE",
            "url": "http://localhost:5000/api/cart/clear",
            "header": [
              {
                "key": "Authorization",
                "value": "Bearer YOUR_TOKEN_HERE"
              }
            ]
          }
        }
      ]
    },
    {
      "name": "Orders",
      "item": [
        {
          "name": "Place Order",
          "request": {
            "method": "POST",
            "url": "http://localhost:5000/api/orders",
            "header": [
              {
                "key": "Authorization",
                "value": "Bearer YOUR_TOKEN_HERE"
              },
              {
                "key": "Content-Type",
                "value": "application/json"
              }
            ],
            "body": {
              "mode": "raw",
              "raw": "{\n  \"items\": [\n    {\n      \"productId\": \"PRODUCT_ID\",\n      \"name\": \"Product Name\",\n      \"quantity\": 2,\n      \"price\": 99.99\n    }\n  ],\n  \"paymentMethod\": \"COD\"\n}"
            }
          }
        },
        {
          "name": "Get User Orders",
          "request": {
            "method": "GET",
            "url": "http://localhost:5000/api/orders?page=1&limit=10",
            "header": [
              {
                "key": "Authorization",
                "value": "Bearer YOUR_TOKEN_HERE"
              }
            ]
          }
        },
        {
          "name": "Get Order by ID",
          "request": {
            "method": "GET",
            "url": "http://localhost:5000/api/orders/ORDER_ID",
            "header": [
              {
                "key": "Authorization",
                "value": "Bearer YOUR_TOKEN_HERE"
              }
            ]
          }
        },
        {
          "name": "Update Order Status",
          "request": {
            "method": "PUT",
            "url": "http://localhost:5000/api/orders/ORDER_ID/status",
            "header": [
              {
                "key": "Authorization",
                "value": "Bearer YOUR_ADMIN_TOKEN"
              },
              {
                "key": "Content-Type",
                "value": "application/json"
              }
            ],
            "body": {
              "mode": "raw",
              "raw": "{\n  \"status\": \"Confirmed\"\n}"
            }
          }
        },
        {
          "name": "Cancel Order",
          "request": {
            "method": "PUT",
            "url": "http://localhost:5000/api/orders/ORDER_ID/cancel",
            "header": [
              {
                "key": "Authorization",
                "value": "Bearer YOUR_TOKEN_HERE"
              }
            ]
          }
        }
      ]
    },
    {
      "name": "Users",
      "item": [
        {
          "name": "Get User Profile",
          "request": {
            "method": "GET",
            "url": "http://localhost:5000/api/users/profile",
            "header": [
              {
                "key": "Authorization",
                "value": "Bearer YOUR_TOKEN_HERE"
              }
            ]
          }
        },
        {
          "name": "Update Profile",
          "request": {
            "method": "PUT",
            "url": "http://localhost:5000/api/users/profile",
            "header": [
              {
                "key": "Authorization",
                "value": "Bearer YOUR_TOKEN_HERE"
              },
              {
                "key": "Content-Type",
                "value": "application/json"
              }
            ],
            "body": {
              "mode": "raw",
              "raw": "{\n  \"name\": \"Updated Name\",\n  \"paymentPreference\": \"Card\"\n}"
            }
          }
        },
        {
          "name": "Add Address",
          "request": {
            "method": "POST",
            "url": "http://localhost:5000/api/users/address",
            "header": [
              {
                "key": "Authorization",
                "value": "Bearer YOUR_TOKEN_HERE"
              },
              {
                "key": "Content-Type",
                "value": "application/json"
              }
            ],
            "body": {
              "mode": "raw",
              "raw": "{\n  \"label\": \"Home\",\n  \"street\": \"123 Main Street\",\n  \"city\": \"Thimphu\",\n  \"state\": \"Thimphu\",\n  \"country\": \"Bhutan\",\n  \"postalCode\": \"11001\"\n}"
            }
          }
        },
        {
          "name": "Add to Wishlist",
          "request": {
            "method": "POST",
            "url": "http://localhost:5000/api/users/wishlist",
            "header": [
              {
                "key": "Authorization",
                "value": "Bearer YOUR_TOKEN_HERE"
              },
              {
                "key": "Content-Type",
                "value": "application/json"
              }
            ],
            "body": {
              "mode": "raw",
              "raw": "{\n  \"productId\": \"PRODUCT_ID\"\n}"
            }
          }
        },
        {
          "name": "Remove from Wishlist",
          "request": {
            "method": "DELETE",
            "url": "http://localhost:5000/api/users/wishlist/PRODUCT_ID",
            "header": [
              {
                "key": "Authorization",
                "value": "Bearer YOUR_TOKEN_HERE"
              }
            ]
          }
        }
      ]
    },
    {
      "name": "Reviews",
      "item": [
        {
          "name": "Create Review",
          "request": {
            "method": "POST",
            "url": "http://localhost:5000/api/reviews",
            "header": [
              {
                "key": "Authorization",
                "value": "Bearer YOUR_TOKEN_HERE"
              },
              {
                "key": "Content-Type",
                "value": "application/json"
              }
            ],
            "body": {
              "mode": "raw",
              "raw": "{\n  \"productId\": \"PRODUCT_ID\",\n  \"rating\": 5,\n  \"comment\": \"Great product! Highly recommend.\"\n}"
            }
          }
        },
        {
          "name": "Get Product Reviews",
          "request": {
            "method": "GET",
            "url": "http://localhost:5000/api/reviews/product/PRODUCT_ID?page=1&limit=10",
            "header": []
          }
        }
      ]
    },
    {
      "name": "Sellers",
      "item": [
        {
          "name": "Get All Sellers",
          "request": {
            "method": "GET",
            "url": "http://localhost:5000/api/sellers?page=1&limit=10",
            "header": []
          }
        },
        {
          "name": "Get Seller Profile",
          "request": {
            "method": "GET",
            "url": "http://localhost:5000/api/sellers/SELLER_ID",
            "header": []
          }
        },
        {
          "name": "Become a Seller",
          "request": {
            "method": "POST",
            "url": "http://localhost:5000/api/sellers",
            "header": [
              {
                "key": "Authorization",
                "value": "Bearer YOUR_TOKEN_HERE"
              },
              {
                "key": "Content-Type",
                "value": "application/json"
              }
            ],
            "body": {
              "mode": "raw",
              "raw": "{\n  \"storeName\": \"My Store\",\n  \"description\": \"Welcome to my store!\"\n}"
            }
          }
        },
        {
          "name": "Update Seller Profile",
          "request": {
            "method": "PUT",
            "url": "http://localhost:5000/api/sellers/profile",
            "header": [
              {
                "key": "Authorization",
                "value": "Bearer YOUR_SELLER_TOKEN"
              },
              {
                "key": "Content-Type",
                "value": "application/json"
              }
            ],
            "body": {
              "mode": "raw",
              "raw": "{\n  \"storeName\": \"Updated Store Name\",\n  \"description\": \"Updated description\"\n}"
            }
          }
        }
      ]
    },
    {
      "name": "Analytics",
      "item": [
        {
          "name": "Monthly Revenue",
          "request": {
            "method": "GET",
            "url": "http://localhost:5000/api/analytics/revenue?month=6&year=2026",
            "header": [
              {
                "key": "Authorization",
                "value": "Bearer YOUR_ADMIN_TOKEN"
              }
            ]
          }
        },
        {
          "name": "Top Products",
          "request": {
            "method": "GET",
            "url": "http://localhost:5000/api/analytics/top-products?limit=10",
            "header": [
              {
                "key": "Authorization",
                "value": "Bearer YOUR_ADMIN_TOKEN"
              }
            ]
          }
        },
        {
          "name": "Low Stock Products",
          "request": {
            "method": "GET",
            "url": "http://localhost:5000/api/analytics/low-stock",
            "header": [
              {
                "key": "Authorization",
                "value": "Bearer YOUR_ADMIN_TOKEN"
              }
            ]
          }
        },
        {
          "name": "Trending Products",
          "request": {
            "method": "GET",
            "url": "http://localhost:5000/api/analytics/trending?limit=10",
            "header": []
          }
        }
      ]
    },
    {
      "name": "Admin",
      "item": [
        {
          "name": "Dashboard Stats",
          "request": {
            "method": "GET",
            "url": "http://localhost:5000/api/admin/dashboard",
            "header": [
              {
                "key": "Authorization",
                "value": "Bearer YOUR_ADMIN_TOKEN"
              }
            ]
          }
        },
        {
          "name": "Get All Users",
          "request": {
            "method": "GET",
            "url": "http://localhost:5000/api/admin/users?page=1&limit=10&role=customer",
            "header": [
              {
                "key": "Authorization",
                "value": "Bearer YOUR_ADMIN_TOKEN"
              }
            ]
          }
        },
        {
          "name": "Delete User",
          "request": {
            "method": "DELETE",
            "url": "http://localhost:5000/api/admin/users/USER_ID",
            "header": [
              {
                "key": "Authorization",
                "value": "Bearer YOUR_ADMIN_TOKEN"
              }
            ]
          }
        },
        {
          "name": "Update User Role",
          "request": {
            "method": "PUT",
            "url": "http://localhost:5000/api/admin/users/USER_ID/role",
            "header": [
              {
                "key": "Authorization",
                "value": "Bearer YOUR_ADMIN_TOKEN"
              },
              {
                "key": "Content-Type",
                "value": "application/json"
              }
            ],
            "body": {
              "mode": "raw",
              "raw": "{\n  \"role\": \"seller\"\n}"
            }
          }
        }
      ]
    }
  ]
}
